deltatfidf/DeltaTfidfTransformer.py
deltatfidf/DeltaTfidfVectorizer.py
deltatfidf/__init__.py
deltatfidf/tests/__init__.py
deltatfidf/tests/test_vectorizer.py
deltatfidf-0.1.dist-info/LICENSE
deltatfidf-0.1.dist-info/METADATA
deltatfidf-0.1.dist-info/WHEEL
deltatfidf-0.1.dist-info/top_level.txt
deltatfidf-0.1.dist-info/RECORD
